MANIFEST.in
README.txt
setup.cfg
setup.py
Wiki_XMLRPC_Extensions/ForkWikiContent.py
Wiki_XMLRPC_Extensions/ListPages.py
Wiki_XMLRPC_Extensions/ReceiveFiles.py
Wiki_XMLRPC_Extensions/SendFiles.py
Wiki_XMLRPC_Extensions/__init__.py
Wiki_XMLRPC_Extensions/examples/ExampleWiki.py
wiki_xmlrpc_extensions.egg-info/PKG-INFO
wiki_xmlrpc_extensions.egg-info/SOURCES.txt
wiki_xmlrpc_extensions.egg-info/dependency_links.txt
wiki_xmlrpc_extensions.egg-info/entry_points.txt
wiki_xmlrpc_extensions.egg-info/namespace_packages.txt
wiki_xmlrpc_extensions.egg-info/not-zip-safe
wiki_xmlrpc_extensions.egg-info/requires.txt
wiki_xmlrpc_extensions.egg-info/top_level.txt