Metadata-Version: 1.0
Name: wiki-xmlrpc-extensions
Version: 0.2.3
Summary: wiki xmlrpc tools for interacting with a MoinMoin Wiki
Home-page: https://utils.icg.kfa-juelich.de/docs/wiki-xmlrpc-extensions/
Author: Reimar Bauer
Author-email: rb.proj@googlemail.com
License: Gnu GPL
Keywords: MoinMoin,xmlrpc
Platform: any
Classifier: D
Classifier: e
Classifier: v
Classifier: e
Classifier: l
Classifier: o
Classifier: p
Classifier: m
Classifier: e
Classifier: n
Classifier: t
Classifier:  
Classifier: S
Classifier: t
Classifier: a
Classifier: t
Classifier: u
Classifier: s
Classifier:  
Classifier: :
Classifier: :
Classifier:  
Classifier: 5
Classifier:  
Classifier: -
Classifier:  
Classifier: P
Classifier: r
Classifier: o
Classifier: d
Classifier: u
Classifier: c
Classifier: t
Classifier: i
Classifier: o
Classifier: n
Classifier: /
Classifier: S
Classifier: t
Classifier: a
Classifier: b
Classifier: l
Classifier: e
